altar_cli/__init__.py
altar_cli/cli.py
altar_cli/configs.py
altar_cli/resolver.py
altar_cli/utils.py
pyaltar_cli-0.1.0.dist-info/METADATA
pyaltar_cli-0.1.0.dist-info/WHEEL
pyaltar_cli-0.1.0.dist-info/entry_points.txt
pyaltar_cli-0.1.0.dist-info/RECORD
